{"GlobalPropertiesHash":"LuuoLk8TkaNd07Bg3NtdSap303Z+R33CIXXKPJaws9c=","FingerprintPatternsHash":"gq3WsqcKBUGTSNle7RKKyXRIwh7M8ccEqOqYvIzoM04=","PropertyOverridesHash":"8ZRc1sGeVrPBx4lD717BgRaQekyh78QKV9SKsdt638U=","InputHashes":["tHz6Q6IeUKpqfFjm6s/2QWmEwxkkd2NNo94SOyQOcvs=","pyQUixVl5\u002BDEQk2kmi1a0yBAhLHamrJt4jGzAJ1l6jk=","XS1GYu4UmuTe2ulj8C21HeyAqOLKG4B3MdOmtsOC/Eo=","DHpBtvMD0k5ergd\u002BeRk/a7kqzLN9fre3a0Au6NUK5CM=","ix4oStI9G2Z4i6aFleg6vB5SeT\u002BEpAT8XKwT8QMMJIo=","QxAnOrFvrSrIshAuF4596dK4Er4qnPaWkrAwrkIoogw="],"CachedAssets":{"tHz6Q6IeUKpqfFjm6s/2QWmEwxkkd2NNo94SOyQOcvs=":{"Identity":"C:\\Users\\100646133\\Documents\\transaction summarise\\TransactionApproval\\wwwroot\\js\\universal-agent.js","SourceId":"TransactionApproval","SourceType":"Discovered","ContentRoot":"C:\\Users\\100646133\\Documents\\transaction summarise\\TransactionApproval\\wwwroot\\","BasePath":"/","RelativePath":"js/universal-agent#[.{fingerprint}]?.js","AssetKind":"All","AssetMode":"All","AssetRole":"Primary","AssetMergeBehavior":null,"AssetMergeSource":"","RelatedAsset":null,"AssetTraitName":null,"AssetTraitValue":null,"Fingerprint":"ikxag6gxs0","Integrity":"jg9rIYM5CMWjbrJAB\u002Bdpv3ghXz2alBZgu2EInSTYt6w=","CopyToOutputDirectory":"Never","CopyToPublishDirectory":"PreserveNewest","OriginalItemSpec":"wwwroot\\js\\universal-agent.js","FileLength":6178,"LastWriteTime":"2026-07-14T14:57:51.1815121+00:00"}},"CachedCopyCandidates":{}}